__init__.py
pyldcn.py
pyldcn-0.4.dist-info/LICENSE
pyldcn-0.4.dist-info/METADATA
pyldcn-0.4.dist-info/WHEEL
pyldcn-0.4.dist-info/top_level.txt
pyldcn-0.4.dist-info/RECORD
