Metadata-Version: 2.1
Name: pyldcn
Version: 0.4
Summary: Python-native implementation of LdcnLib
Author-email: Philipp Peterseil <philipp.peterseil@jku.at>
Project-URL: Homepage, https://github.com/ppeterseil/pyldcn
Project-URL: Bug Tracker, https://github.com/ppeterseil/pyldcn/issues
Classifier: Programming Language :: Python :: 3
Classifier: License :: OSI Approved :: MIT License
Classifier: Operating System :: OS Independent
Requires-Python: >=3.7
License-File: LICENSE
Requires-Dist: pyserial (~=3.4)
